repochecker/__init__.py
repochecker/git_info.py
gitrepochecker-0.2.3.dist-info/LICENSE
gitrepochecker-0.2.3.dist-info/METADATA
gitrepochecker-0.2.3.dist-info/WHEEL
gitrepochecker-0.2.3.dist-info/entry_points.txt
gitrepochecker-0.2.3.dist-info/top_level.txt
gitrepochecker-0.2.3.dist-info/RECORD
