Metadata-Version: 2.1
Name: gitrepochecker
Version: 0.2.3
Summary: Command line tool to check all git repositories in a directory
Author: Oli
Author-email: Oli <oli@olillin.com>
Maintainer-email: Oli <oli@olillin.com>
License: MIT License
Project-URL: Bug Reports, https://github.com/olillin/RepoChecker/issues
Project-URL: Source, https://github.com/olillin/RepoChecker
Classifier: Development Status :: 3 - Alpha
Classifier: License :: OSI Approved :: MIT License
Classifier: Programming Language :: Python :: 3
License-File: LICENSE
Requires-Dist: colorama
